BrownieCutter/BrownieCutter.py
BrownieCutter/__init__.py
BrownieCutter/__main__.py
BrownieCutter-0.1.20.dist-info/LICENSE.md
BrownieCutter-0.1.20.dist-info/METADATA
BrownieCutter-0.1.20.dist-info/WHEEL
BrownieCutter-0.1.20.dist-info/entry_points.txt
BrownieCutter-0.1.20.dist-info/top_level.txt
BrownieCutter-0.1.20.dist-info/RECORD
