Metadata-Version: 2.2
Name: BrownieCutter
Version: 0.1.20
Summary: Quick script to create new python project
Home-page: https://github.com/thiswillbeyourgithub/BrownieCutter
License: GPLv3
Keywords: cookiecutter,pypi,install,package,python,minimal,minimalist,tool
Classifier: Programming Language :: Python :: 3
Classifier: License :: OSI Approved :: GNU General Public License v3 (GPLv3)
Classifier: Operating System :: OS Independent
Requires-Python: >=3.11
License-File: LICENSE.md
Requires-Dist: fire>=0.6.0
Requires-Dist: beartype>=0.19.0
Dynamic: classifier
Dynamic: description
Dynamic: description-content-type
Dynamic: home-page
Dynamic: keywords
Dynamic: license
Dynamic: requires-dist
Dynamic: requires-python
Dynamic: summary
